README.md
setup.py
FastSync.egg-info/PKG-INFO
FastSync.egg-info/SOURCES.txt
FastSync.egg-info/dependency_links.txt
FastSync.egg-info/entry_points.txt
FastSync.egg-info/requires.txt
FastSync.egg-info/top_level.txt
sync/__init__.py
sync/receiver.py
sync/sender.py