Metadata-Version: 1.0
Name: FastSync
Version: 0.2.0.5
Summary: Event driven fast synchronization tool
Home-page: https://github.com/iMuduo/FastSync
Author: Muduo
Author-email: imuduo@163.com
License: Apache License
Keywords: sync
Platform: UNKNOWN
